{
    "Image_0": 1,
    "Image_1": 1,
    "Image_2": 4,
    "Image_3": 2,
    "Image_4": 4,
    "Image_5": 3,
    "Image_6": 4,
    "Image_7": 0,
    "Image_8": 2,
    "Image_9": 2,
    "Image_10": 2,
    "Image_11": 1,
    "Image_12": 3,
    "Image_13": 4,
    "Image_14": 2,
    "Image_15": 2,
    "Image_16": 0,
    "Image_17": 1,
    "Image_18": 3,
    "Image_19": 2,
    "Image_20": 1,
    "Image_21": 0,
    "Image_22": 2,
    "Image_23": 0,
    "Image_24": 4,
    "Image_25": 3,
    "Image_26": 2,
    "Image_27": 2,
    "Image_28": 1,
    "Image_29": 3,
    "Image_30": 3,
    "Image_31": 1,
    "Image_32": 4,
    "Image_33": 2,
    "Image_34": 1,
    "Image_35": 2,
    "Image_36": 2,
    "Image_37": 2,
    "Image_38": 1,
    "Image_39": 2,
    "Image_40": 2,
    "Image_41": 1,
    "Image_42": 0,
    "Image_43": 2,
    "Image_44": 1,
    "Image_45": 4,
    "Image_46": 2,
    "Image_47": 2,
    "Image_48": 0,
    "Image_49": 0,
    "Image_50": 1,
    "Image_51": 2,
    "Image_52": 2,
    "Image_53": 2,
    "Image_54": 0,
    "Image_55": 1,
    "Image_56": 3,
    "Image_57": 1,
    "Image_58": 1,
    "Image_59": 0,
    "Image_60": 2,
    "Image_61": 0,
    "Image_62": 4,
    "Image_63": 3,
    "Image_64": 4,
    "Image_65": 2,
    "Image_66": 1,
    "Image_67": 1,
    "Image_68": 3,
    "Image_69": 2,
    "Image_70": 0,
    "Image_71": 1,
    "Image_72": 2,
    "Image_73": 2,
    "Image_74": 1,
    "Image_75": 0,
    "Image_76": 0,
    "Image_77": 0,
    "Image_78": 2,
    "Image_79": 2,
    "Image_80": 2,
    "Image_81": 1,
    "Image_82": 2,
    "Image_83": 4,
    "Image_84": 2,
    "Image_85": 2,
    "Image_86": 2,
    "Image_87": 1,
    "Image_88": 2,
    "Image_89": 4,
    "Image_90": 2,
    "Image_91": 0,
    "Image_92": 2,
    "Image_93": 1,
    "Image_94": 4,
    "Image_95": 1,
    "Image_96": 2,
    "Image_97": 2,
    "Image_98": 4,
    "Image_99": 2
}