{
    "epochs": "Not provided",
    "training_losses": "Not provided",
    "final_accuracy": "Not provided",
    "results": {
        "mode": "deccs",
        "training_losses": [
            [
                0.8355862855911255,
                0.7372210383415222,
                0.6676627397537231,
                0.6371460556983948
            ],
            [
                0.6745726108551026,
                0.6678763389587402,
                0.6677769303321839,
                0.6650983572006226
            ],
            [
                0.6655635118484498,
                0.6621641397476197,
                0.6620376944541931,
                0.66047043800354
            ],
            [
                0.6672584176063537,
                0.6654229283332824,
                0.664763331413269,
                0.6635924100875854
            ],
            [
                0.669205367565155,
                0.6667974710464477,
                0.6635556817054749,
                0.6595532298088074
            ],
            [
                0.6612760901451111,
                0.652595067024231,
                0.646094024181366,
                0.6419019579887391
            ],
            [
                0.6435017704963684,
                0.6377498030662536,
                0.6335585594177247,
                0.6301917433738708
            ],
            [
                0.6360293388366699,
                0.6307164907455445,
                0.6288717865943909,
                0.6256200790405273
            ],
            [
                0.624948239326477,
                0.6191444396972656,
                0.6166919708251953,
                0.6157126426696777
            ],
            [
                0.6251400470733642,
                0.6202421188354492,
                0.6144668579101562,
                0.6139919877052307
            ]
        ],
        "metrics": {
            "acc": 0.29375,
            "ari": 0.001749550549365528,
            "nmi": 0.6318435311982094,
            "silhouette": 0.20860521495342255,
            "clusters": [
                9,
                15,
                2,
                30,
                27,
                26,
                36,
                7,
                10,
                11,
                25,
                4,
                42,
                9,
                0,
                5,
                19,
                13,
                22,
                38,
                24,
                13,
                1,
                33,
                16,
                19,
                0,
                38,
                22,
                7,
                11,
                24,
                12,
                18,
                18,
                40,
                37,
                34,
                26,
                4,
                10,
                35,
                35,
                44,
                11,
                27,
                23,
                19,
                6,
                23,
                1,
                33,
                40,
                20,
                10,
                32,
                13,
                44,
                16,
                40,
                6,
                21,
                23,
                30,
                9,
                28,
                23,
                16,
                2,
                6,
                33,
                22,
                12,
                25,
                3,
                23,
                0,
                34,
                4,
                6,
                23,
                19,
                17,
                14,
                37,
                44,
                29,
                37,
                43,
                29,
                0,
                38,
                21,
                44,
                2,
                29,
                28,
                23,
                41,
                11,
                3,
                43,
                11,
                4,
                2,
                6,
                5,
                44,
                20,
                42,
                19,
                8,
                8,
                18,
                3,
                11,
                20,
                32,
                22,
                17,
                8,
                3,
                5,
                20,
                31,
                18,
                2,
                13,
                20,
                1,
                31,
                3,
                0,
                17,
                14,
                0,
                40,
                3,
                12,
                29,
                7,
                6,
                41,
                14,
                21,
                1,
                18,
                19,
                1,
                39,
                5,
                15,
                36,
                24,
                39,
                21,
                19,
                28,
                28,
                14
            ]
        }
    },
    "final_acc": 0.29375,
    "final_nmi": 0.6318435311982094,
    "final_silhouette": 0.20860521495342255
}